bayesint/__init__.py
bayesint/intervals.py
bayesint/random_variables.py
bayesint/table_measures.py
bayesint/table_tests.py
bayesint/version.py
bayesint-1.0.3.dist-info/LICENSE
bayesint-1.0.3.dist-info/METADATA
bayesint-1.0.3.dist-info/WHEEL
bayesint-1.0.3.dist-info/top_level.txt
bayesint-1.0.3.dist-info/RECORD
