Metadata-Version: 2.1
Name: bayesint
Version: 1.0.3
Summary: Bayesian credible intervals for ratios
Home-page: https://github.com/PublicHealthEngland/bayesint
Author: Public Health England
Author-email: thomas.finnie@phe.gov.uk
Maintainer: Public Health England
License: Open Government Licence 3.0
Platform: UNKNOWN
Classifier: Programming Language :: Python
Classifier: Programming Language :: Python :: 2.7
Classifier: Programming Language :: Python :: 3.5
Classifier: Programming Language :: Python :: 3.6
Classifier: Programming Language :: Python :: 3.7
Classifier: License :: Other/Proprietary License
Classifier: Natural Language :: English
Classifier: Topic :: Scientific/Engineering :: Information Analysis
Classifier: Intended Audience :: Science/Research
Classifier: Operating System :: OS Independent
Requires-Python: >=2.7.14, !=3.0.*, !=3.1.*, !=3.3.*, !=3.4.*, >=3.5.5, >=3.6.6
Requires-Dist: scipy (>=0.19.1)
Requires-Dist: sympy (>=1.1.1)
Requires-Dist: numpy (>=1.13.3)
